ChangeLog
LICENSE
MANIFEST.in
PumpkinLB.py
README.md
README.rst
example.cfg
setup.py
PumpkinLB.egg-info/PKG-INFO
PumpkinLB.egg-info/SOURCES.txt
PumpkinLB.egg-info/dependency_links.txt
PumpkinLB.egg-info/top_level.txt
pumpkinlb/__init__.py
pumpkinlb/config.py
pumpkinlb/constants.py
pumpkinlb/listener.py
pumpkinlb/log.py
pumpkinlb/usage.py
pumpkinlb/worker.py