Metadata-Version: 1.1
Name: PumpkinLB
Version: 1.4
Summary: A simple, fast, pure-python load balancer
Home-page: https://github.com/kata198/PumpkinLB
Author: Tim Savannah
Author-email: kata198@gmail.com
License: GPLv3
Keywords: load balancer,load balance,python,balance,lb,http,socket,port,forward,tcp,fast,server,network
Platform: UNKNOWN
Classifier: Development Status :: 4 - Beta
Classifier: Programming Language :: Python
Classifier: License :: OSI Approved :: GNU Lesser General Public License v3 (LGPLv3)
Classifier: Programming Language :: Python :: 2
Classifier: Programming Language :: Python :: 2.7
Classifier: Topic :: Internet
Classifier: Topic :: Internet :: WWW/HTTP
Classifier: Topic :: System :: Distributed Computing
Classifier: Topic :: System :: Networking
Provides: PumpkinLB
